{
    "symbol": "KLAY/USDT:USDT",
    "timestamp": 1719169967378,
    "datetime": "2024-06-23T19:12:47.378Z",
    "high": 0.1615,
    "low": 0.1558,
    "bid": null,
    "bidVolume": null,
    "ask": null,
    "askVolume": null,
    "vwap": 0.1592,
    "open": 0.1592,
    "close": 0.1559,
    "last": 0.1559,
    "previousClose": null,
    "change": -0.0033,
    "percentage": -2.073,
    "average": 0.15755,
    "baseVolume": 21459291.1,
    "quoteVolume": 3415932.789,
    "info": {
        "symbol": "KLAYUSDT",
        "priceChange": "-0.0033",
        "priceChangePercent": "-2.073",
        "weightedAvgPrice": "0.1592",
        "lastPrice": "0.1559",
        "lastQty": "244.9",
        "openPrice": "0.1592",
        "highPrice": "0.1615",
        "lowPrice": "0.1558",
        "volume": "21459291.1",
        "quoteVolume": "3415932.7890",
        "openTime": "1719083520000",
        "closeTime": "1719169967378",
        "firstId": "109039425",
        "lastId": "109067985",
        "count": "28561"
    }
}