{
    "symbol": "NEXO/USDT",
    "timestamp": 1719169626722,
    "datetime": "2024-06-23T19:07:06.722Z",
    "high": 1.252,
    "low": 1.201,
    "bid": 1.214,
    "bidVolume": 449.02,
    "ask": 1.215,
    "askVolume": 165.98,
    "vwap": 1.22305082,
    "open": 1.223,
    "close": 1.214,
    "last": 1.214,
    "previousClose": 1.223,
    "change": -0.009,
    "percentage": -0.736,
    "average": 1.2185,
    "baseVolume": 524373.59,
    "quoteVolume": 641335.54709,
    "info": {
        "symbol": "NEXOUSDT",
        "priceChange": "-0.00900000",
        "priceChangePercent": "-0.736",
        "weightedAvgPrice": "1.22305082",
        "prevClosePrice": "1.22300000",
        "lastPrice": "1.21400000",
        "lastQty": "24.48000000",
        "bidPrice": "1.21400000",
        "bidQty": "449.02000000",
        "askPrice": "1.21500000",
        "askQty": "165.98000000",
        "openPrice": "1.22300000",
        "highPrice": "1.25200000",
        "lowPrice": "1.20100000",
        "volume": "524373.59000000",
        "quoteVolume": "641335.54709000",
        "openTime": "1719083226722",
        "closeTime": "1719169626722",
        "firstId": "12266272",
        "lastId": "12276095",
        "count": "9824"
    }
}