{
    "symbol": "SEI/USDT:USDT",
    "timestamp": 1719170011270,
    "datetime": "2024-06-23T19:13:31.270Z",
    "high": 0.3621,
    "low": 0.3425,
    "bid": null,
    "bidVolume": null,
    "ask": null,
    "askVolume": null,
    "vwap": 0.3536506,
    "open": 0.3573,
    "close": 0.3494,
    "last": 0.3494,
    "previousClose": null,
    "change": -0.0079,
    "percentage": -2.211,
    "average": 0.35335,
    "baseVolume": 69375429.0,
    "quoteVolume": 24534661.6702,
    "info": {
        "symbol": "SEIUSDT",
        "priceChange": "-0.0079000",
        "priceChangePercent": "-2.211",
        "weightedAvgPrice": "0.3536506",
        "lastPrice": "0.3494000",
        "lastQty": "57",
        "openPrice": "0.3573000",
        "highPrice": "0.3621000",
        "lowPrice": "0.3425000",
        "volume": "69375429",
        "quoteVolume": "24534661.6702000",
        "openTime": "1719083580000",
        "closeTime": "1719170011270",
        "firstId": "219941014",
        "lastId": "220075539",
        "count": "134526"
    }
}