{
    "symbol": "SOL/USDT:USDT",
    "timestamp": 1719169945126,
    "datetime": "2024-06-23T19:12:25.126Z",
    "high": 135.064,
    "low": 130.329,
    "bid": null,
    "bidVolume": null,
    "ask": null,
    "askVolume": null,
    "vwap": 133.2064,
    "open": 134.036,
    "close": 131.754,
    "last": 131.754,
    "previousClose": null,
    "change": -2.282,
    "percentage": -1.703,
    "average": 132.895,
    "baseVolume": 6081053.0,
    "quoteVolume": 810035282.976,
    "info": {
        "symbol": "SOLUSDT",
        "priceChange": "-2.2820",
        "priceChangePercent": "-1.703",
        "weightedAvgPrice": "133.2064",
        "lastPrice": "131.7540",
        "lastQty": "1",
        "openPrice": "134.0360",
        "highPrice": "135.0640",
        "lowPrice": "130.3290",
        "volume": "6081053",
        "quoteVolume": "810035282.9760",
        "openTime": "1719083520000",
        "closeTime": "1719169945126",
        "firstId": "1624103862",
        "lastId": "1624778585",
        "count": "674719"
    }
}