{
    "symbol": "TFUEL/USDT",
    "timestamp": 1719169029784,
    "datetime": "2024-06-23T18:57:09.784Z",
    "high": 0.08,
    "low": 0.0724,
    "bid": 0.07584,
    "bidVolume": 559.0,
    "ask": 0.07592,
    "askVolume": 334.0,
    "vwap": 0.07632955,
    "open": 0.07291,
    "close": 0.07586,
    "last": 0.07586,
    "previousClose": 0.07287,
    "change": 0.00295,
    "percentage": 4.046,
    "average": 0.074385,
    "baseVolume": 39418668.0,
    "quoteVolume": 3008809.1787,
    "info": {
        "symbol": "TFUELUSDT",
        "priceChange": "0.00295000",
        "priceChangePercent": "4.046",
        "weightedAvgPrice": "0.07632955",
        "prevClosePrice": "0.07287000",
        "lastPrice": "0.07586000",
        "lastQty": "334.00000000",
        "bidPrice": "0.07584000",
        "bidQty": "559.00000000",
        "askPrice": "0.07592000",
        "askQty": "334.00000000",
        "openPrice": "0.07291000",
        "highPrice": "0.08000000",
        "lowPrice": "0.07240000",
        "volume": "39418668.00000000",
        "quoteVolume": "3008809.17870000",
        "openTime": "1719082629784",
        "closeTime": "1719169029784",
        "firstId": "60890500",
        "lastId": "60930538",
        "count": "40039"
    }
}