{
    "symbol": "USDP/USDT",
    "timestamp": 1719169486100,
    "datetime": "2024-06-23T19:04:46.100Z",
    "high": 1.0008,
    "low": 1.0003,
    "bid": 1.0006,
    "bidVolume": 5074.0,
    "ask": 1.0007,
    "askVolume": 346.0,
    "vwap": 1.00055821,
    "open": 1.0006,
    "close": 1.0007,
    "last": 1.0007,
    "previousClose": 1.0006,
    "change": 0.0001,
    "percentage": 0.01,
    "average": 1.00065,
    "baseVolume": 187760.0,
    "quoteVolume": 187864.809,
    "info": {
        "symbol": "USDPUSDT",
        "priceChange": "0.00010000",
        "priceChangePercent": "0.010",
        "weightedAvgPrice": "1.00055821",
        "prevClosePrice": "1.00060000",
        "lastPrice": "1.00070000",
        "lastQty": "19.00000000",
        "bidPrice": "1.00060000",
        "bidQty": "5074.00000000",
        "askPrice": "1.00070000",
        "askQty": "346.00000000",
        "openPrice": "1.00060000",
        "highPrice": "1.00080000",
        "lowPrice": "1.00030000",
        "volume": "187760.00000000",
        "quoteVolume": "187864.80900000",
        "openTime": "1719083086100",
        "closeTime": "1719169486100",
        "firstId": "1684093",
        "lastId": "1687482",
        "count": "3390"
    }
}