{
    "symbol": "USDT/ARS",
    "timestamp": 1719169737215,
    "datetime": "2024-06-23T19:08:57.215Z",
    "high": 1305.0,
    "low": 1298.7,
    "bid": 1300.3,
    "bidVolume": 2615.0,
    "ask": 1300.4,
    "askVolume": 100.0,
    "vwap": 1301.25103446,
    "open": 1303.0,
    "close": 1300.3,
    "last": 1300.3,
    "previousClose": 1303.0,
    "change": -2.7,
    "percentage": -0.207,
    "average": 1301.65,
    "baseVolume": 1000571.0,
    "quoteVolume": 1301994048.8,
    "info": {
        "symbol": "USDTARS",
        "priceChange": "-2.70000000",
        "priceChangePercent": "-0.207",
        "weightedAvgPrice": "1301.25103446",
        "prevClosePrice": "1303.00000000",
        "lastPrice": "1300.30000000",
        "lastQty": "366.00000000",
        "bidPrice": "1300.30000000",
        "bidQty": "2615.00000000",
        "askPrice": "1300.40000000",
        "askQty": "100.00000000",
        "openPrice": "1303.00000000",
        "highPrice": "1305.00000000",
        "lowPrice": "1298.70000000",
        "volume": "1000571.00000000",
        "quoteVolume": "1301994048.80000000",
        "openTime": "1719083337215",
        "closeTime": "1719169737215",
        "firstId": "8296920",
        "lastId": "8354246",
        "count": "57327"
    }
}