{
    "symbol": "WAXP/USDT:USDT",
    "timestamp": 1719170013549,
    "datetime": "2024-06-23T19:13:33.549Z",
    "high": 0.04052,
    "low": 0.03879,
    "bid": null,
    "bidVolume": null,
    "ask": null,
    "askVolume": null,
    "vwap": 0.0399266,
    "open": 0.03989,
    "close": 0.03912,
    "last": 0.03912,
    "previousClose": null,
    "change": -0.00077,
    "percentage": -1.93,
    "average": 0.039505,
    "baseVolume": 72599155.0,
    "quoteVolume": 2898636.46159,
    "info": {
        "symbol": "WAXPUSDT",
        "priceChange": "-0.0007700",
        "priceChangePercent": "-1.930",
        "weightedAvgPrice": "0.0399266",
        "lastPrice": "0.0391200",
        "lastQty": "284",
        "openPrice": "0.0398900",
        "highPrice": "0.0405200",
        "lowPrice": "0.0387900",
        "volume": "72599155",
        "quoteVolume": "2898636.4615900",
        "openTime": "1719083580000",
        "closeTime": "1719170013549",
        "firstId": "33429576",
        "lastId": "33461346",
        "count": "31771"
    }
}